{
  "exercise": "09_radiosonda_picaro_full",
  "goes_to_chirpstack": true,
  "hardware": "LILYGO T-Beam Supreme (ESP32-S3 + SX1262 + L76K + BME280)",
  "framework": "ESP-IDF v5.5 (RadioLib)",
  "region": "US915",
  "subband": 2,
  "lorawan_version": "1.0.x",
  "activation": "OTAA",
  "class": "A",
  "fport": 10,
  "decoder": "chirpstack/decoder.js",
  "device_profile_name": "Radiosonda-PICARO-Full-US915",
  "dev_eui": "70b3d57ed0090901",
  "join_eui": "0000000000000000",
  "app_key": "50494341524f3039a5a5a5a5a5a5a5a5",
  "note": "En LoRaWAN 1.0.x la AppKey se registra en el campo 'Application key' (web) o 'nwkKey' (REST)."
}
